dfwsgroup/__init__.py
dfwsgroup/__main__.py
dfwsgroup/android/__init__.py
dfwsgroup/android/handle.py
dfwsgroup/android/script.py
dfwsgroup/android/Fastbot_Android/fastbot-thirdpart.jar
dfwsgroup/android/Fastbot_Android/framework.jar
dfwsgroup/android/Fastbot_Android/monkeyq.jar
dfwsgroup/common/__init__.py
dfwsgroup/common/cli.py
dfwsgroup/common/command.py
dfwsgroup/common/custom.py
dfwsgroup/common/process.py
dfwsgroup/common/scaffold.py
dfwsgroup/config/abl.strings
dfwsgroup/config/awl.strings
dfwsgroup/config/max.config
dfwsgroup/config/max.strings
dfwsgroup/config/max.xpath.actions
dfwsgroup/data/command.json
dfwsgroup-1.0.8.dist-info/LICENSE
dfwsgroup-1.0.8.dist-info/METADATA
dfwsgroup-1.0.8.dist-info/WHEEL
dfwsgroup-1.0.8.dist-info/top_level.txt
dfwsgroup-1.0.8.dist-info/RECORD
